README.rst
setup.py
nengo_spinnaker/__init__.py
nengo_spinnaker/config.py
nengo_spinnaker/partition.py
nengo_spinnaker/rc.py
nengo_spinnaker/simulator.py
nengo_spinnaker.egg-info/PKG-INFO
nengo_spinnaker.egg-info/SOURCES.txt
nengo_spinnaker.egg-info/dependency_links.txt
nengo_spinnaker.egg-info/entry_points.txt
nengo_spinnaker.egg-info/not-zip-safe
nengo_spinnaker.egg-info/requires.txt
nengo_spinnaker.egg-info/top_level.txt
nengo_spinnaker/binaries/nengo_ensemble.aplx
nengo_spinnaker/binaries/nengo_ensemble_profiled.aplx
nengo_spinnaker/binaries/nengo_filter.aplx
nengo_spinnaker/binaries/nengo_mc_player.aplx
nengo_spinnaker/binaries/nengo_rx.aplx
nengo_spinnaker/binaries/nengo_tx.aplx
nengo_spinnaker/binaries/nengo_value_sink.aplx
nengo_spinnaker/binaries/nengo_value_source.aplx
nengo_spinnaker/builder/__init__.py
nengo_spinnaker/builder/builder.py
nengo_spinnaker/builder/connection.py
nengo_spinnaker/builder/ensemble.py
nengo_spinnaker/builder/model.py
nengo_spinnaker/builder/netlist.py
nengo_spinnaker/builder/node.py
nengo_spinnaker/builder/ports.py
nengo_spinnaker/netlist/__init__.py
nengo_spinnaker/netlist/netlist.py
nengo_spinnaker/netlist/objects.py
nengo_spinnaker/netlist/utils.py
nengo_spinnaker/node_io/__init__.py
nengo_spinnaker/node_io/ethernet.py
nengo_spinnaker/operators/__init__.py
nengo_spinnaker/operators/filter.py
nengo_spinnaker/operators/lif.py
nengo_spinnaker/operators/sdp_receiver.py
nengo_spinnaker/operators/sdp_transmitter.py
nengo_spinnaker/operators/value_sink.py
nengo_spinnaker/operators/value_source.py
nengo_spinnaker/regions/__init__.py
nengo_spinnaker/regions/filters.py
nengo_spinnaker/regions/keyspaces.py
nengo_spinnaker/regions/list.py
nengo_spinnaker/regions/matrix.py
nengo_spinnaker/regions/profiler.py
nengo_spinnaker/regions/recording.py
nengo_spinnaker/regions/region.py
nengo_spinnaker/regions/utils.py
nengo_spinnaker/scripts/__init__.py
nengo_spinnaker/scripts/nengo_spinnaker_setup.py
nengo_spinnaker/utils/__init__.py
nengo_spinnaker/utils/application.py
nengo_spinnaker/utils/collections.py
nengo_spinnaker/utils/config.py
nengo_spinnaker/utils/itertools.py
nengo_spinnaker/utils/keyspaces.py
nengo_spinnaker/utils/model.py
nengo_spinnaker/utils/neurons.py
nengo_spinnaker/utils/paths.py
