Metadata-Version: 1.1
Name: nengo-spinnaker
Version: 0.4.0
Summary: Tools for simulating neural models generated using Nengo on the SpiNNaker platform
Home-page: https://github.com/project-rig/nengo_spinnaker
Author: University of Manchester and University of Waterloo
Author-email: UNKNOWN
License: GPLv2
Keywords: spinnaker nengo neural cognitive simulation
Platform: UNKNOWN
Classifier: Development Status :: 3 - Alpha
Classifier: Intended Audience :: Science/Research
Classifier: License :: OSI Approved :: GNU General Public License v2 (GPLv2)
Classifier: Operating System :: POSIX :: Linux
Classifier: Operating System :: Microsoft :: Windows
Classifier: Operating System :: MacOS
Classifier: Programming Language :: Python :: 2
Classifier: Programming Language :: Python :: 2.7
Classifier: Programming Language :: Python :: 3
Classifier: Programming Language :: Python :: 3.4
Classifier: Topic :: Scientific/Engineering
